sp_bh_at/__init__.py
sp_bh_at/data/output/geo/01_aprm.7z
sp_bh_at/data/output/geo/06_bacia_alto_tiete.7z
sp_bh_at/data/output/geo/101_rmsp.7z
sp_bh_at/data/output/geo/16_hidrografia.7z
sp_bh_at/data/output/geo/17_hidrografia_complementar.7z
sp_bh_at/data/output/geo/45_subbacias.7z
sp_bh_at/data/output/geo/57_area_protegida_revisao.7z
sp_bh_at/data/output/geo/58_area_protegida_zona_amortecimento.7z
sp_bh_at/data/output/geo/apps_hidrografia.7z
sp_bh_at/data/output/geo/apps_nascentes.7z
sp_bh_at/data/output/geo/municipios ugrhi 6.7z
sp_bh_at/data/output/geo/municípios da região metropolitana de são paulo.7z
sp_bh_at/data/output/geo/reservatórios_rmsp.7z
sp_bh_at/data/output/geo/áreas contaminadas e reabilitadas na ugrhi 6 - ano 2020.7z
sp_bh_at-0.0.11.dist-info/LICENSE
sp_bh_at-0.0.11.dist-info/METADATA
sp_bh_at-0.0.11.dist-info/WHEEL
sp_bh_at-0.0.11.dist-info/top_level.txt
sp_bh_at-0.0.11.dist-info/RECORD
