Metadata-Version: 2.1
Name: sp-bh-at
Version: 0.0.11
Summary: Dados Espaciais do Comitê de Bacias do Alto Tietê 
Home-page: https://github.com/open-geodata/sp_bh_at
Author: Michel Metran
Author-email: michelmetran@gmail.com
Keywords: python,dados espaciais,geoprocessamento
Classifier: Programming Language :: Python :: 3
Classifier: License :: OSI Approved :: MIT License
Classifier: Operating System :: OS Independent
Classifier: Natural Language :: Portuguese
Classifier: Intended Audience :: Developers
Requires-Python: >=3
License-File: LICENSE
